{
  "coc.preferences.colorSupport": true,
  "coc.preferences.formatOnSaveFiletypes": ["python", "css", "markdown", "Markdown", "javascript", "javascriptreact", "typescript", "typescriptreact", "json"],
  "codeLens.enable": true,
  "diagnostic.displayByAle": false,
  "diagnostic.enableSign": true,
  "diagnostic.messageTarget": "float",
  "diagnostic.refreshAfterSave": false,
  "diagnostic.refreshOnInsertMode": true,
  "diagnostic.virtualText": true,
  "python.analysis.logLevel": "Trace",
  "python.formatting.provider": "black",
  "python.jediEnabled": true,
  "python.jediPath": "/usr/local/lib/python3.7/site-packages",
  "python.linting.mypyEnabled": true,
  "python.linting.pylintEnabled": true,
  "signature.enable": true,
  "signature.target": "echo",
  "suggest.echodocSupport": true,
  "tslint.autoFixOnSave": false,
  "tslint.jsEnable": true,
  "tslint.suppressWhileTypeErrorsPresent": false,
  "tsserver.log": "verbose",
  "tsserver.npm": "/usr/local/bin/npm",
  "tsserver.trace.server": "verbose",
  "yaml.schemas": {
    "kubernetes": "*.y*ml",
    "http://json.schemastore.org/ansible-stable-2.7": "playbook/**/*.y*ml"
  }
}
